primo_entrega4_master_python_diegodd5/__init__.py
primo_entrega4_master_python_diegodd5/primo.py
primo_entrega4_master_python_diegodd5-0.1.dist-info/LICENSE.txt
primo_entrega4_master_python_diegodd5-0.1.dist-info/METADATA
primo_entrega4_master_python_diegodd5-0.1.dist-info/WHEEL
primo_entrega4_master_python_diegodd5-0.1.dist-info/top_level.txt
primo_entrega4_master_python_diegodd5-0.1.dist-info/RECORD
