Metadata-Version: 2.1
Name: primo-entrega4-master-python-diegodd5
Version: 0.1
Summary: Para calcular primos a fuerza bruta
Home-page: UNKNOWN
Author: Diego
Author-email: diegodiazdiaz@gmail.com
License: GNU GPL v3
Keywords: prime numbers
Platform: UNKNOWN
Classifier: Development Status :: 5 - Production/Stable
Classifier: Intended Audience :: Developers
Classifier: Topic :: Utilities
Classifier: License :: OSI Approved :: GNU General Public License v3 (GPLv3)
Classifier: Programming Language :: Python :: 3
Classifier: Operating System :: OS Independent
